nova.py
nova_cli-0.1.1.dist-info/METADATA
nova_cli-0.1.1.dist-info/WHEEL
nova_cli-0.1.1.dist-info/entry_points.txt
nova_cli-0.1.1.dist-info/top_level.txt
nova_cli-0.1.1.dist-info/RECORD
