Metadata-Version: 2.4
Name: nova-cli
Version: 0.1.1
Summary: Command-line interface for Nova Chain
Author: Logan Whitcomb
Requires-Dist: requests>=2.31
Requires-Dist: PyNaCl>=1.5
Requires-Dist: bech32>=1.2.0
